LICENSE
README.md
bgetlib/__init__.py
bgetlib/api.py
bgetlib/codec.py
bgetlib/models.py
bgetlib/streamer.py
bgetlib/utils.py
bgetlib-3.2.8.dist-info/LICENSE
bgetlib-3.2.8.dist-info/WHEEL
bgetlib-3.2.8.dist-info/METADATA
bgetlib-3.2.8.dist-info/RECORD
