Metadata-Version: 2.1
Name: bgetlib
Version: 3.2.8
Summary: A BiliBili API library
Home-page: https://bgetlib.docs.josephcz.xyz/
License: MIT
Keywords: bilibili
Author: Joseph Chris
Author-email: joseph@josephcz.xyz
Requires-Python: >=3.8,<4.0
Classifier: License :: OSI Approved :: MIT License
Classifier: Operating System :: OS Independent
Classifier: Programming Language :: Python :: 3
Classifier: Programming Language :: Python :: 3.8
Classifier: Programming Language :: Python :: 3.9
Classifier: Programming Language :: Python :: 3.10
Classifier: Programming Language :: Python :: 3.11
Classifier: Programming Language :: Python :: 3
Requires-Dist: requests (>=2.25.1,<2.26.0)
Project-URL: Repository, https://github.com/baobao1270/bgetlib.git
